{
  "image": "oll_45.png",
  "oll_case": "OLL 45",
  "pll_case": "Solved",
  "visible_stickers": [
    "W",
    "W",
    "G",
    "W",
    "W",
    "R",
    "W",
    "O",
    "G",
    "B",
    "W",
    "R",
    "W",
    "W",
    "W"
  ],
  "top_face": [
    "W",
    "W",
    "G",
    "W",
    "W",
    "R",
    "W",
    "O",
    "G"
  ],
  "front_top_row": [
    "B",
    "W",
    "R"
  ],
  "right_top_row": [
    "W",
    "W",
    "W"
  ],
  "full_state": {
    "U": [
      "W",
      "W",
      "G",
      "W",
      "W",
      "R",
      "W",
      "O",
      "G"
    ],
    "D": [
      "Y",
      "Y",
      "Y",
      "Y",
      "Y",
      "Y",
      "Y",
      "Y",
      "Y"
    ],
    "F": [
      "B",
      "W",
      "R",
      "R",
      "R",
      "R",
      "R",
      "R",
      "R"
    ],
    "B": [
      "O",
      "B",
      "B",
      "O",
      "O",
      "O",
      "O",
      "O",
      "O"
    ],
    "L": [
      "O",
      "G",
      "R",
      "G",
      "G",
      "G",
      "G",
      "G",
      "G"
    ],
    "R": [
      "W",
      "W",
      "W",
      "B",
      "B",
      "B",
      "B",
      "B",
      "B"
    ]
  }
}